minecraft_data/__init__.py
minecraft_data/tools.py
minecraft_data_standalone-3.21.0.dist-info/METADATA
minecraft_data_standalone-3.21.0.dist-info/WHEEL
minecraft_data_standalone-3.21.0.dist-info/licenses/LICENSE
minecraft_data_standalone-3.21.0.dist-info/RECORD
