Metadata-Version: 2.1
Name: minecraft_data_standalone
Version: 3.21.0
Summary: Provide easy access to minecraft data in python
Project-URL: Homepage, https://github.com/EnzoPB/python-minecraft-data
Project-URL: Issues, https://github.com/EnzoPB/python-minecraft-data
Author-email: Enzo PB <enzo@enzopb.me>
License-File: LICENSE
Classifier: License :: OSI Approved :: MIT License
Classifier: Operating System :: OS Independent
Classifier: Programming Language :: Python :: 3
Requires-Python: >=3.8
